pyke/__init__.py
pyke/ask_tty.py
pyke/ask_wx.py
pyke/bc_rule.py
pyke/condensedPrint.py
pyke/contexts.py
pyke/fact_base.py
pyke/fc_rule.py
pyke/goal.py
pyke/immutable_dict.py
pyke/knowledge_base.py
pyke/knowledge_engine.py
pyke/krb_traceback.py
pyke/pattern.py
pyke/qa_helpers.py
pyke/question_base.py
pyke/rule_base.py
pyke/special.py
pyke/target_pkg.py
pyke/test.py
pyke/unique.py
pyke/user_question.py
pyke/krb_compiler/__init__.py
pyke/krb_compiler/compiler.krb
pyke/krb_compiler/compiler_bc.py
pyke/krb_compiler/helpers.py
pyke/krb_compiler/kfbparser.py
pyke/krb_compiler/kfbparser_tables.py
pyke/krb_compiler/kqb_parser.py
pyke/krb_compiler/krbparser.py
pyke/krb_compiler/krbparser_tables.py
pyke/krb_compiler/scanner.py
pyke/krb_compiler/scanner_tables.py
pyke/krb_compiler/ply/README
pyke/krb_compiler/ply/README.pyke
pyke/krb_compiler/ply/__init__.py
pyke/krb_compiler/ply/lex.py
pyke/krb_compiler/ply/yacc.py
scitools_pyke-1.1.1.dist-info/LICENSE
scitools_pyke-1.1.1.dist-info/METADATA
scitools_pyke-1.1.1.dist-info/WHEEL
scitools_pyke-1.1.1.dist-info/top_level.txt
scitools_pyke-1.1.1.dist-info/RECORD
